dmengine/__init__.py
dmengine/__main__.py
dmengine/analysis.py
dmengine/calculation.py
dmengine/contexts.py
dmengine/exponents.py
dmengine/features.py
dmengine/insertion.py
dmengine/meta.py
dmengine/outcontexts.py
dmengine/readjustments.py
dmengine/rules.py
dmengine/tools.py
dmengine/types.py
dmengine/vis.py
dmengine/reporting/__init__.py
dmengine/reporting/backend.py
dmengine/reporting/common.py
dmengine/reporting/contexts.py
dmengine/reporting/examples.py
dmengine/reporting/features.py
dmengine/reporting/inputs.py
dmengine/reporting/log.py
dmengine/reporting/paradigms.py
dmengine/reporting/readjustments.py
dmengine/reporting/report.py
dmengine/reporting/rules.py
dmengine/reporting/template.tex
dmengine/reporting/tools.py
dmengine/reporting/vis.py
dmengine/vendor/__init__.py
dmengine/vendor/oset/__init__.py
dmengine/vendor/oset/pyoset.py
dmengine-0.4.1.dist-info/licenses/LICENSE.txt
dmengine-0.4.1.dist-info/METADATA
dmengine-0.4.1.dist-info/WHEEL
dmengine-0.4.1.dist-info/entry_points.txt
dmengine-0.4.1.dist-info/top_level.txt
dmengine-0.4.1.dist-info/RECORD
