Metadata-Version: 2.4
Name: dmengine
Version: 0.4.1
Summary: Distributed Morphology calculator
Author-email: Sebastian Bank <sebastian.bank@uni-leipzig.de>
License-Expression: MIT
Project-URL: Homepage, https://github.com/xflr6/dmengine
Project-URL: Changelog, https://github.com/xflr6/dmengine/blob/master/CHANGES.rst
Project-URL: Issue Tracker, https://github.com/xflr6/dmengine/issues
Project-URL: CI, https://github.com/xflr6/dmengine/actions
Project-URL: Coverage, https://app.codecov.io/gh/xflr6/dmengine
Keywords: DM,Halle,Marantz,impoverishment,fission,linguistics
Platform: any
Classifier: Development Status :: 4 - Beta
Classifier: Environment :: Console
Classifier: Intended Audience :: Developers
Classifier: Intended Audience :: Science/Research
Classifier: Operating System :: OS Independent
Classifier: Programming Language :: Python :: 3
Classifier: Programming Language :: Python :: 3.10
Classifier: Programming Language :: Python :: 3.11
Classifier: Programming Language :: Python :: 3.12
Classifier: Programming Language :: Python :: 3.13
Classifier: Programming Language :: Python :: 3.14
Requires-Python: >=3.10
License-File: LICENSE.txt
Requires-Dist: PyYAML
Dynamic: license-file
